dlomix/__init__.py
dlomix/__main__.py
dlomix/_metadata.py
dlomix/config.py
dlomix/constants.py
dlomix/detectability_model_constants.py
dlomix/types.py
dlomix/data/__init__.py
dlomix/data/charge_state.py
dlomix/data/dataset.py
dlomix/data/dataset_config.py
dlomix/data/dataset_utils.py
dlomix/data/detectability.py
dlomix/data/fragment_ion_intensity.py
dlomix/data/ion_mobility.py
dlomix/data/retention_time.py
dlomix/data/processing/__init__.py
dlomix/data/processing/feature_extractors.py
dlomix/data/processing/feature_tables.py
dlomix/data/processing/processors.py
dlomix/data/processing/pickled_feature_dicts/mz_diff.pkl
dlomix/data/processing/pickled_feature_dicts/red_smiles.pkl
dlomix/data/processing/pickled_feature_dicts/saved_ac_count.pkl
dlomix/data/processing/pickled_feature_dicts/saved_gained_atoms.pkl
dlomix/data/processing/pickled_feature_dicts/saved_loss_atoms.pkl
dlomix/eval/__init__.py
dlomix/eval/chargestate.py
dlomix/eval/chargestate_torch.py
dlomix/eval/rt_eval.py
dlomix/eval/rt_eval_torch.py
dlomix/layers/__init__.py
dlomix/layers/attention.py
dlomix/layers/attention_torch.py
dlomix/layers/bi_gru_seq_encoder_torch.py
dlomix/layers/gru_seq_decoder_torch.py
dlomix/losses/__init__.py
dlomix/losses/intensity.py
dlomix/losses/intensity_torch.py
dlomix/losses/ionmob_torch.py
dlomix/models/__init__.py
dlomix/models/base.py
dlomix/models/chargestate.py
dlomix/models/chargestate_torch.py
dlomix/models/deepLC.py
dlomix/models/detectability.py
dlomix/models/detectability_torch.py
dlomix/models/ionmob_torch.py
dlomix/models/prosit.py
dlomix/models/prosit_torch.py
dlomix/pipelines/__init__.py
dlomix/pipelines/pipeline.py
dlomix/reports/DetectabilityReport.py
dlomix/reports/IntensityReport.py
dlomix/reports/Report.py
dlomix/reports/RetentionTimeReport.py
dlomix/reports/RetentionTimeReportModelComparisonWandb.py
dlomix/reports/RetentionTimeReportRunComparisonWandb.py
dlomix/reports/__init__.py
dlomix/reports/postprocessing.py
dlomix-0.2.2.dist-info/licenses/LICENSE
dlomix-0.2.2.dist-info/METADATA
dlomix-0.2.2.dist-info/WHEEL
dlomix-0.2.2.dist-info/top_level.txt
dlomix-0.2.2.dist-info/RECORD
