Metadata-Version: 2.4
Name: dlomix
Version: 0.2.2
Summary: Deep Learning for Proteomics
Home-page: https://github.com/wilhelm-lab/dlomix
Author: Wilhelm Lab
Author-email: o.shouman@tum.de
Classifier: Programming Language :: Python :: 3
Classifier: Programming Language :: Python :: 3.9
Classifier: License :: OSI Approved :: MIT License
Classifier: Operating System :: OS Independent
Classifier: Topic :: Scientific/Engineering :: Bio-Informatics
Classifier: Development Status :: 1 - Planning
Classifier: Intended Audience :: Science/Research
License-File: LICENSE
Requires-Dist: datasets
Requires-Dist: huggingface_hub
Requires-Dist: fpdf
Requires-Dist: pandas
Requires-Dist: numpy
Requires-Dist: matplotlib
Requires-Dist: scikit-learn
Requires-Dist: pyarrow
Requires-Dist: seaborn
Provides-Extra: dev
Requires-Dist: pytest>=3.9; extra == "dev"
Requires-Dist: pytest-cov; extra == "dev"
Requires-Dist: black; extra == "dev"
Requires-Dist: twine; extra == "dev"
Requires-Dist: setuptools; extra == "dev"
Requires-Dist: wheel; extra == "dev"
Requires-Dist: pylint; extra == "dev"
Requires-Dist: tensorflow<2.16,>=2.13; extra == "dev"
Requires-Dist: torch; extra == "dev"
Requires-Dist: torchvision; extra == "dev"
Provides-Extra: wandb
Requires-Dist: wandb>=0.15; extra == "wandb"
Provides-Extra: tensorflow
Requires-Dist: tensorflow<2.16,>=2.13; extra == "tensorflow"
Provides-Extra: tf
Requires-Dist: tensorflow<2.16,>=2.13; extra == "tf"
Provides-Extra: torch
Requires-Dist: torch; extra == "torch"
Requires-Dist: torchvision; extra == "torch"
Provides-Extra: pytorch
Requires-Dist: torch; extra == "pytorch"
Requires-Dist: torchvision; extra == "pytorch"
Provides-Extra: lightning
Requires-Dist: lightning; extra == "lightning"
Dynamic: author
Dynamic: author-email
Dynamic: classifier
Dynamic: description
Dynamic: description-content-type
Dynamic: home-page
Dynamic: license-file
Dynamic: provides-extra
Dynamic: requires-dist
Dynamic: summary
